password_gen/__init__.py
password_gen/password.py
password_gen/utils.py
psswd_manager-0.1.2.dist-info/METADATA
psswd_manager-0.1.2.dist-info/WHEEL
psswd_manager-0.1.2.dist-info/top_level.txt
psswd_manager-0.1.2.dist-info/RECORD
