Metadata-Version: 2.1
Name: psswd_manager
Version: 0.1.2
Summary: A library to generate and manage passwords in your scripts.
Home-page: https://github.com/sammy-ulfh/Python-packages
Author: Sammy-ulfh
